{
  "allMembers": {
    "231d19ef-5d6f-45d8-9c28-44c571987b27": {
      "firstName": "Aadhiti",
      "lastName": "Ghankota",
      "nickname": "",
      "image": "aadhiti-ghankota-0.jpg",
      "roles": [
        "Senior Advisor"
      ],
      "linkedIn": "",
      "website": "",
      "email": "aadhitighankota@berkeley.edu"
    },
    "b26925d9-ed5a-4c18-bcc0-cccf929d06c9": {
      "firstName": "Abigail",
      "lastName": "Delgado",
      "nickname": "Abby",
      "image": "abigail-delgado-0.jpg",
      "roles": [
        ""
      ],
      "linkedIn": "https://www.linkedin.com/in/abigail-gee-delgado",
      "website": "",
      "email": "abigaildelgado@berkeley.edu"
    },
    "6e486461-c847-4eb4-b0c0-dea09904ecf8": {
      "firstName": "Abdul",
      "lastName": "Karim",
      "nickname": "",
      "image": "abdul-karim-0.jpg",
      "roles": [
        ""
      ],
      "linkedIn": "https://www.linkedin.com/in/abdulfk",
      "website": "https://www.linkedin.com/in/abdulfk",
      "email": "afkarim@berkeley.edu"
    },
    "94b3ddba-5af1-48e8-9b9f-7c6d952ec9ec": {
      "firstName": "Adam",
      "lastName": "Goldstein",
      "nickname": "",
      "image": "adam-goldstein-0.jpg",
      "roles": [
        "[DeCal] Fullstack TA"
      ],
      "linkedIn": "https://www.linkedin.com/in/adam-j-goldstein",
      "website": "",
      "email": "adamgoldstein@berkeley.edu"
    },
    "0421f855-bba2-40b7-87c7-303bbc99f95e": {
      "firstName": "Aditya",
      "lastName": "Bhawal",
      "nickname": "",
      "image": "aditya-bhawal-0.jpg",
      "roles": [
        ""
      ],
      "linkedIn": "https://www.linkedin.com/in/adityabhawal/",
      "website": "",
      "email": "adbhawal@berkeley.edu"
    },
    "4947071e-4886-4af5-95bd-bf907dedb474": {
      "firstName": "Albert",
      "lastName": "Tian",
      "nickname": "",
      "image": "albert-tian-0.jpg",
      "roles": [
        ""
      ],
      "linkedIn": "https://www.linkedin.com/in/albert-tian/'",
      "website": "https://www.github.com/albTian",
      "email": ""
    },
    "ed69747d-dd74-464f-8b79-81fc2e00d773": {
      "firstName": "Alex",
      "lastName": "Wu",
      "nickname": "",
      "image": "alex-wu-0.jpg",
      "roles": [
        ""
      ],
      "linkedIn": "",
      "website": "",
      "email": ""
    },
    "a6c64e23-03dd-4a47-a5f5-bb416c58d338": {
      "firstName": "Alexis",
      "lastName": "Kim",
      "nickname": "",
      "image": "alexis-kim-0.jpg",
      "roles": [
        ""
      ],
      "linkedIn": "https://www.linkedin.com/in/alexisskim",
      "website": "https://www.alexiskim.me",
      "email": "alexis-kim@berkeley.edu"
    },
    "c2e00e6b-976e-47c5-be2f-efc6d08af327": {
      "firstName": "Ali",
      "lastName": "Ansari",
      "nickname": "",
      "image": "ali-ansari-0.jpg",
      "roles": [
        ""
      ],
      "linkedIn": "",
      "website": "",
      "email": ""
    },
    "18e74d58-2799-406c-8239-555726efba42": {
      "firstName": "Alina",
      "lastName": "Wang",
      "nickname": "",
      "image": "alina-wang-0.jpg",
      "roles": [
        ""
      ],
      "linkedIn": "https://www.linkedin.com/in/wangerful/",
      "website": "",
      "email": "alina.wang@berkeley.edu"
    },
    "a86d7c13-cf31-4c79-8c95-a1dfcde7381a": {
      "firstName": "Amish",
      "lastName": "Gupta",
      "nickname": "",
      "image": "amish-gupta-0.jpg",
      "roles": [
        "[Exec] VP Bootcamp"
      ],
      "linkedIn": "https://www.linkedin.com/in/amishgupta678/",
      "website": "",
      "email": "amish@berkeley.edu"
    },
    "044913a7-b349-4d23-b1ea-0402e55127ed": {
      "firstName": "YeEun",
      "lastName": "Kwon",
      "nickname": "Amy",
      "image": "yeeun-kwon-0.jpg",
      "roles": [
        ""
      ],
      "linkedIn": "https://www.linkedin.com/in/amy-kwon-928872142/",
      "website": "",
      "email": "amykwon@berkeley.edu"
    },
    "a85e67c9-5246-480f-b64c-be76fe8e8cfb": {
      "firstName": "Amy",
      "lastName": "Yang",
      "nickname": "",
      "image": "amy-yang-0.jpg",
      "roles": [
        ""
      ],
      "linkedIn": "https://www.linkedin.com/in/amy-yang-3632331bb/",
      "website": "",
      "email": "ayang24@berkeley.edu"
    },
    "acf8db27-8965-44f7-b16b-bf87995231e6": {
      "firstName": "Andy",
      "lastName": "Ngo",
      "nickname": "",
      "image": "andy-ngo-0.jpg",
      "roles": [
        "[MET] Member"
      ],
      "linkedIn": "https://www.linkedin.com/in/andytngo",
      "website": "",
      "email": "ango9031@berkeley.edu"
    },
    "44402e83-d106-4e1e-9296-60178c66b677": {
      "firstName": "Angel",
      "lastName": "Mau",
      "nickname": "",
      "image": "angel-mau-0.jpg",
      "roles": [
        "[DeCal] Fullstack TA",
        "[MET] Member"
      ],
      "linkedIn": "https://www.linkedin/angelmau",
      "website": "",
      "email": "angelmau@berkeley.edu"
    },
    "23978789-c7df-4596-a6dc-0d1241436081": {
      "firstName": "Angela",
      "lastName": "Li",
      "nickname": "",
      "image": "angela-li-0.jpg",
      "roles": [
        "[Exec] VP Internal"
      ],
      "linkedIn": "https://www.linkedin.com/in/totalangela",
      "website": "https://www.totalangela.github.io",
      "email": "totalangela@berkeley.edu"
    },
    "89b3a373-1f45-4bca-9a8f-a56b04ca3380": {
      "firstName": "Aniruddh",
      "lastName": "Chennapragada",
      "nickname": "Ani",
      "image": "aniruddh-chennapragada-0.jpg",
      "roles": [
        ""
      ],
      "linkedIn": "https://www.linkedin.com/in/aniruddh-chennapragada-976278179/",
      "website": "",
      "email": "anic@berkeley.edu"
    },
    "fec43be9-6273-49a3-84fe-6d8e9741d43d": {
      "firstName": "Aniruddha",
      "lastName": "Vangala",
      "nickname": "Ani",
      "image": "aniruddha-vangala-0.jpg",
      "roles": [
        ""
      ],
      "linkedIn": "",
      "website": "",
      "email": ""
    },
    "3090cfbf-9fe9-4a0b-9599-6b956b3a9d0c": {
      "firstName": "Anish",
      "lastName": "Shanbhag",
      "nickname": "",
      "image": "anish-shanbhag-0.jpg",
      "roles": [
        "Senior Advisor"
      ],
      "linkedIn": "https://www.linkedin.com/in/anish-shanbhag",
      "website": "",
      "email": "anish.shanbhag@berkeley.edu"
    },
    "cb5e4030-4d8e-4066-a729-fb3789b90968": {
      "firstName": "Anjan",
      "lastName": "Bharadwaj",
      "nickname": "",
      "image": "anjan-bharadwaj-0.jpg",
      "roles": [
        "[MET] Member"
      ],
      "linkedIn": "https://www.linkedin.com/in/anjanbharadwaj/",
      "website": "https://www.anjanbharadwaj.com/",
      "email": "anjanb@berkeley.edu"
    },
    "9abba05a-21a7-482f-b85c-7dcece75e52f": {
      "firstName": "Anna",
      "lastName": "Hagiwara",
      "nickname": "",
      "image": "anna-hagiwara-0.jpg",
      "roles": [
        "[Industry] Product Manager"
      ],
      "linkedIn": "https://www.linkedin.com/in/anna-hagiwara",
      "website": "",
      "email": "ahagiwara@berkeley.edu"
    },
    "87a82a09-9462-4d99-8ebf-b46a6d458b43": {
      "firstName": "Viansa",
      "lastName": "Schmulbach",
      "nickname": "Ansa",
      "image": "viansa-schmulbach-0.jpg",
      "roles": [
        ""
      ],
      "linkedIn": "https://www.linkedin.com/in/viansa-s/",
      "website": "",
      "email": "ansa@berkeley.edu"
    },
    "e8ba4d2d-0a97-470b-8ddc-68b04a837643": {
      "firstName": "Artem",
      "lastName": "Tkachuk",
      "nickname": "Art",
      "image": "artem-tkachuk-0.jpg",
      "roles": [
        ""
      ],
      "linkedIn": "https://www.linkedin.com/in/artemtkachuk/",
      "website": "https://www.artemtkachuk.me",
      "email": "atkachuk@berkeley.edu"
    },
    "58dba9e7-b85b-4a50-b35e-5442e6c3635a": {
      "firstName": "Arushi",
      "lastName": "Somani",
      "nickname": "",
      "image": "arushi-somani-0.jpg",
      "roles": [
        ""
      ],
      "linkedIn": "https://www.linkedin.com/in/arushisomani/",
      "website": "http://amks.me",
      "email": ""
    },
    "4fe84e26-f0fc-4090-a03a-bd55a5e523a4": {
      "firstName": "Ashley",
      "lastName": "Zheng",
      "nickname": "",
      "image": "ashley-zheng-0.jpg",
      "roles": [
        ""
      ],
      "linkedIn": "https://www.linkedin.com/in/ashley-zheng-5553151a8",
      "website": "",
      "email": "ashley.zheng@berkeley.edu"
    },
    "97ae6e72-57cd-4249-a8f4-a5a497405638": {
      "firstName": "Atharva",
      "lastName": "Mehendale",
      "nickname": "",
      "image": "atharva-mehendale-0.jpg",
      "roles": [
        ""
      ],
      "linkedIn": "",
      "website": "",
      "email": ""
    },
    "519190da-3933-48d3-9fb2-c0dbce64316c": {
      "firstName": "Avinash",
      "lastName": "Rao",
      "nickname": "",
      "image": "avinash-rao-0.jpg",
      "roles": [
        ""
      ],
      "linkedIn": "https://www.linkedin.com/in/avinashrao2002/",
      "website": "",
      "email": "avinashrao2002@berkeley.edu"
    },
    "5143a5c1-9f07-4371-bd16-47eb044ab280": {
      "firstName": "Ayaka",
      "lastName": "Chou",
      "nickname": "",
      "image": "ayaka-chou-0.jpg",
      "roles": [
        ""
      ],
      "linkedIn": "https://www.linkedin.com/in/ayaka-chou",
      "website": "",
      "email": "ayakachou@berkeley.edu"
    },
    "77162a8b-2651-4bfa-9d8a-b7f75fe1f954": {
      "firstName": "Caelin",
      "lastName": "Sutch",
      "nickname": "",
      "image": "caelin-sutch-0.jpg",
      "roles": [
        ""
      ],
      "linkedIn": "https://www.linkedin.com/in/caelinsutch/",
      "website": "https://www.caelinsutch.com/",
      "email": ""
    },
    "17864f2d-c332-4d1b-8509-6b1b90a06953": {
      "firstName": "Chengyin",
      "lastName": "Li",
      "nickname": "Cass",
      "image": "chengyin-li-0.jpg",
      "roles": [
        "[MET] Member"
      ],
      "linkedIn": "https://www.linkedin.com/in/chengyin-li/",
      "website": "https://www.cassli.webflow.io",
      "email": "chengyin@berkeley.edu"
    },
    "96409aab-4cfe-4069-8953-f1249dd6727b": {
      "firstName": "Chanel",
      "lastName": "Zeng",
      "nickname": "",
      "image": "chanel-zeng-0.jpg",
      "roles": [
        ""
      ],
      "linkedIn": "https://www.linkedin.com/in/chanelzeng/",
      "website": "",
      "email": "zengchanel@berkeley.edu"
    },
    "95760de0-4e8f-40a6-8116-8d0ec6133e41": {
      "firstName": "Cindy",
      "lastName": "Liu",
      "nickname": "",
      "image": "cindy-liu-0.jpg",
      "roles": [
        ""
      ],
      "linkedIn": "https://www.linkedin.com/in/cindy-c-liu/",
      "website": "",
      "email": "liu.cindy@berkeley.edu"
    },
    "0bf8c341-e30e-4655-b20c-e57c97e9e650": {
      "firstName": "Daniel",
      "lastName": "Won",
      "nickname": "",
      "image": "daniel-won-0.jpg",
      "roles": [
        ""
      ],
      "linkedIn": "",
      "website": "",
      "email": ""
    },
    "d28e29cd-c8a9-41ac-8f3a-1294dccce610": {
      "firstName": "Danielle",
      "lastName": "Wong",
      "nickname": "",
      "image": "danielle-wong-0.jpg",
      "roles": [
        "[DeCal] Design TA",
        "[MET] Member"
      ],
      "linkedIn": "https://www.linkedin.com/in/danielle-n-wong/",
      "website": "",
      "email": "daniellenwong@berkeley.edu"
    },
    "092ee936-7c05-4396-95d7-efb9a036d77f": {
      "firstName": "Deniz",
      "lastName": "Demirtas",
      "nickname": "DD",
      "image": "deniz-demirtas-0.jpg",
      "roles": [
        "[Industry] Product Manager",
        "[External Team] Member"
      ],
      "linkedIn": "https://www.linkedin.com/in/deniz-demirtas-827416225/",
      "website": "",
      "email": "denizdemirtas@berkeley.edu"
    },
    "fc1e6f95-5563-40e5-badf-bb6fd8477842": {
      "firstName": "Dhruv",
      "lastName": "Vaish",
      "nickname": "",
      "image": "dhruv-vaish-0.jpg",
      "roles": [
        "Senior Advisor"
      ],
      "linkedIn": "https://www.linkedin.com/in/dhruv-vaish",
      "website": "",
      "email": "dvaish@berkeley.edu"
    },
    "96586d35-e9c8-4310-a464-4db13bc9a924": {
      "firstName": "Dominic",
      "lastName": "deBettencourt",
      "nickname": "",
      "image": "dominic-debettencourt-0.jpg",
      "roles": [
        "[MET] Member"
      ],
      "linkedIn": "https://www.linkedin.com/in/ddebettencourt",
      "website": "https://www.dominicd.me",
      "email": "dominicd@berkeley.edu"
    },
    "198a392a-150e-4d41-b7aa-f3cdcb4e0ee8": {
      "firstName": "Dora",
      "lastName": "Fok",
      "nickname": "",
      "image": "dora-fok-0.jpg",
      "roles": [
        "[Decal] Course Staff"
      ],
      "linkedIn": "",
      "website": "",
      "email": "dorafok@berkeley.edu"
    },
    "9cba7420-3a5d-439a-86d1-fa7fa3ad9920": {
      "firstName": "Edward",
      "lastName": "Luna",
      "nickname": "",
      "image": "edward-luna-0.jpg",
      "roles": [
        ""
      ],
      "linkedIn": "https://www.linkedin.com/in/edwardlunacs/",
      "website": "",
      "email": "mister.luna@berkeley.edu"
    },
    "61662ea7-9daa-41d6-9bde-c61c1a7673e1": {
      "firstName": "Emir",
      "lastName": "Karabeg",
      "nickname": "",
      "image": "emir-karabeg-0.jpg",
      "roles": [
        ""
      ],
      "linkedIn": "",
      "website": "",
      "email": "emirkarabeg@berkeley.edu"
    },
    "1c573912-17b2-48af-8548-780f62243457": {
      "firstName": "Ervin",
      "lastName": "Baccay",
      "nickname": "",
      "image": "ervin-baccay-0.jpg",
      "roles": [
        ""
      ],
      "linkedIn": "",
      "website": "",
      "email": ""
    },
    "69feb8b3-5b2b-43c3-a2b8-405d011cfe06": {
      "firstName": "Ethan",
      "lastName": "Pang",
      "nickname": "",
      "image": "ethan-pang-0.jpg",
      "roles": [
        ""
      ],
      "linkedIn": "https://www.linkedin.com/in/ethanpang5/",
      "website": "https://www.ethanpang5.github.io/",
      "email": "ethanp5@berkeley.edu"
    },
    "4ac17b82-3776-403a-8926-09752efb41b4": {
      "firstName": "Ethan",
      "lastName": "Wu",
      "nickname": "",
      "image": "ethan-wu-0.jpg",
      "roles": [
        ""
      ],
      "linkedIn": "https://www.linkedin.com/in/ethan-wu/",
      "website": "",
      "email": ""
    },
    "b1b77402-80e8-4d9c-ac44-a591a045633d": {
      "firstName": "Evan",
      "lastName": "Quan",
      "nickname": "",
      "image": "evan-quan-0.jpg",
      "roles": [
        ""
      ],
      "linkedIn": "https://www.linkedin.com/in/evqu",
      "website": "https://www.evanq.studio",
      "email": "evan.quan@berkeley.edu"
    },
    "2d4e93a0-7fed-47c2-8ac9-be2cd72a1f23": {
      "firstName": "Ezra",
      "lastName": "Apple",
      "nickname": "",
      "image": "ezra-apple-0.jpg",
      "roles": [
        "[DeCal] Fullstack TA"
      ],
      "linkedIn": "https://www.linkedin.com/in/ezraapple/",
      "website": "",
      "email": "ezraapple@berkeley.edu"
    },
    "3805c4a9-a2e6-4b8e-a698-7cf5843dd63e": {
      "firstName": "Felix",
      "lastName": "Zhu",
      "nickname": "",
      "image": "felix-zhu-0.jpg",
      "roles": [
        "[Decal] Course Staff"
      ],
      "linkedIn": "https://www.linkedin.com/in/felixzhu555",
      "website": "",
      "email": "felixzhu@berkeley.edu"
    },
    "52dc0651-09e5-42d8-bfb3-1ca34cf44d6e": {
      "firstName": "Gabriel",
      "lastName": "Meng",
      "nickname": "Gabe",
      "image": "gabriel-meng-0.jpg",
      "roles": [
        ""
      ],
      "linkedIn": "",
      "website": "",
      "email": ""
    },
    "0380b5db-9eed-4b9c-a840-b538dd766ab2": {
      "firstName": "Genna",
      "lastName": "Gams",
      "nickname": "",
      "image": "genna-gams-0.jpg",
      "roles": [
        "[Exec] VP Bootcamp"
      ],
      "linkedIn": "https://www.linkedin.com/in/genna-gams",
      "website": "https://www.ggams2020.github.io/site",
      "email": "ggams@berkeley.edu"
    },
    "72ad1dda-5b34-4330-8f36-0ed9265df32f": {
      "firstName": "Hector",
      "lastName": "Ramos",
      "nickname": "",
      "image": "hector-ramos-0.jpg",
      "roles": [
        ""
      ],
      "linkedIn": "https://www.linkedin.com/in/hector-ramos-/",
      "website": "",
      "email": ""
    },
    "4cde5e51-5318-4cc1-8f2b-e286c0efd837": {
      "firstName": "Henric",
      "lastName": "Zhang",
      "nickname": "",
      "image": "henric-zhang-0.jpg",
      "roles": [
        "[Decal] Course Staff"
      ],
      "linkedIn": "",
      "website": "",
      "email": "henriczhang@berkeley.edu"
    },
    "679cf4da-672c-4e50-9a62-003b278668bc": {
      "firstName": "Henry",
      "lastName": "Chiu",
      "nickname": "",
      "image": "henry-chiu-0.jpg",
      "roles": [
        ""
      ],
      "linkedIn": "https://www.linkedin.com/in/henryychiu/",
      "website": "http://henrychiu.me",
      "email": ""
    },
    "aad57f0e-745e-433c-a8cc-b8bc423920ee": {
      "firstName": "Hunter",
      "lastName": "Harling",
      "nickname": "",
      "image": "hunter-harling-0.jpg",
      "roles": [
        "[Industry] Product Manager"
      ],
      "linkedIn": "https://www.linkedin.com/mwlite/in/hunterharling",
      "website": "",
      "email": "hunterharling@berkeley.edu"
    },
    "6ceb24d4-6e5c-466e-9e98-0d268434392f": {
      "firstName": "Ikshita",
      "lastName": "Puri",
      "nickname": "Iki",
      "image": "ikshita-puri-0.jpg",
      "roles": [
        ""
      ],
      "linkedIn": "https://www.linkedin.com/mwlite/in/ikshita-puri-3bb3251a3",
      "website": "",
      "email": "ikshitapuri@berkeley.edu"
    },
    "6897bfe7-8b92-4137-ac4f-87165cb55c6d": {
      "firstName": "Isaac",
      "lastName": "Ong",
      "nickname": "",
      "image": "isaac-ong-0.jpg",
      "roles": [
        ""
      ],
      "linkedIn": "https://www.linkedin.com/in/isaacong",
      "website": "https://www.isaacong.me",
      "email": "isaacong@berkeley.edu"
    },
    "ccf2e74e-e2ed-4e67-b51a-abb961f25022": {
      "firstName": "Isabel",
      "lastName": "Zheng",
      "nickname": "",
      "image": "isabel-zheng-0.jpg",
      "roles": [
        "Senior Advisor"
      ],
      "linkedIn": "",
      "website": "",
      "email": "izheng@berkeley.edu"
    },
    "cf42a5e4-e388-466c-948f-5a81cf78a424": {
      "firstName": "Ishan",
      "lastName": "Amin",
      "nickname": "",
      "image": "ishan-amin-0.jpg",
      "roles": [
        "Senior Advisor"
      ],
      "linkedIn": "https://www.linkedin.com/in/ishan-amin-522027174/  ",
      "website": "",
      "email": "ishanthewizard@berkeley.edu"
    },
    "f570c49b-4dc4-4911-8e35-7f96369d873a": {
      "firstName": "Izzie",
      "lastName": "Lau",
      "nickname": "",
      "image": "izzie-lau-0.jpg",
      "roles": [
        ""
      ],
      "linkedIn": "",
      "website": "",
      "email": ""
    },
    "d900637f-a6d1-412e-817c-92d4096027e6": {
      "firstName": "Jackson",
      "lastName": "Wong",
      "nickname": "",
      "image": "jackson-wong-0.jpg",
      "roles": [
        "[Industry] Product Manager",
        "[External Team] Member"
      ],
      "linkedIn": "https://www.linkedin.com/in/jacksontwong/",
      "website": "",
      "email": "wongjt@berkeley.edu"
    },
    "965ee02b-381f-4cfd-ac05-b207bd850e75": {
      "firstName": "James",
      "lastName": "Shin",
      "nickname": "",
      "image": "james-shin-0.jpg",
      "roles": [
        ""
      ],
      "linkedIn": "",
      "website": "",
      "email": ""
    },
    "eaadbbd1-9dfb-40f1-898f-735a78752a39": {
      "firstName": "Jasmine",
      "lastName": "Chen",
      "nickname": "",
      "image": "jasmine-chen-0.jpg",
      "roles": [
        ""
      ],
      "linkedIn": "https://www.linkedin.com/in/jasminewschen/",
      "website": "https://www.jasminewschen.com/",
      "email": ""
    },
    "b667697e-b463-4311-844d-dc399ecdfe68": {
      "firstName": "Jason",
      "lastName": "Duong",
      "nickname": "",
      "image": "jason-duong-0.jpg",
      "roles": [
        "[Industry] Frontend Developer"
      ],
      "linkedIn": "https://www.linkedin.com/in/jasonduongg/",
      "website": "https://www.jasonduongg.github.io/Personal/",
      "email": "jasonduong@berkeley.edu"
    },
    "e33c7668-d94d-45d9-b73c-de84e847f91c": {
      "firstName": "Jazem",
      "lastName": "Siddiqui",
      "nickname": "",
      "image": "jazem-siddiqui-0.jpg",
      "roles": [
        ""
      ],
      "linkedIn": "",
      "website": "",
      "email": ""
    },
    "b8a78c51-a7e4-443d-a822-c499084a9ec8": {
      "firstName": "Jeffrey",
      "lastName": "Huang",
      "nickname": "",
      "image": "jeffrey-huang-0.jpg",
      "roles": [
        ""
      ],
      "linkedIn": "https://www.linkedin.com/in/jeffreyhuang2002/",
      "website": "https://www.jefforee.github.io/jeffreyhuang/",
      "email": "jeff0827@berkeley.edu"
    },
    "41316dcb-9acb-44d8-88bb-7e6241759316": {
      "firstName": "Jiahuang",
      "lastName": "Weng",
      "nickname": "Jenny",
      "image": "jiahuang-weng-0.jpg",
      "roles": [
        "[Exec] VP Design"
      ],
      "linkedIn": "https://www.linkedin.com/in/jennyweng",
      "website": "https://www.jennyweng.com",
      "email": "jennyweng@berkeley.edu"
    },
    "3ac9716b-c6d7-4e89-8ee7-960eb9942c02": {
      "firstName": "Jessica",
      "lastName": "Hwang",
      "nickname": "",
      "image": "jessica-hwang-0.jpg",
      "roles": [
        ""
      ],
      "linkedIn": "",
      "website": "",
      "email": "jyjhwang@berkeley.edu"
    },
    "1c6a78b6-d715-4b75-8ad6-0e3c1ec17acf": {
      "firstName": "Jessica",
      "lastName": "Wu",
      "nickname": "",
      "image": "jessica-wu-0.jpg",
      "roles": [
        ""
      ],
      "linkedIn": "",
      "website": "",
      "email": ""
    },
    "46f88ea2-06f3-4f0a-9db1-d17d1f4cbce7": {
      "firstName": "Jiro",
      "lastName": "Noor",
      "nickname": "",
      "image": "jiro-noor-0.jpg",
      "roles": [
        "[Decal] Course Staff"
      ],
      "linkedIn": "https://www.linkedin.com/in/jiro-ryzard-noor/",
      "website": "",
      "email": "jiro.noor@berkeley.edu"
    },
    "c4e9ec3c-8641-4229-9bf0-a1d8d3a2f914": {
      "firstName": "Jonathan",
      "lastName": "Sun",
      "nickname": "Jon",
      "image": "jonathan-sun-0.jpg",
      "roles": [
        ""
      ],
      "linkedIn": "",
      "website": "",
      "email": "jsun63@berkeley.edu"
    },
    "da68c925-5139-492d-8006-1b6b3b52a866": {
      "firstName": "Joshua",
      "lastName": "Tsai",
      "nickname": "Josh",
      "image": "joshua-tsai-0.jpg",
      "roles": [
        ""
      ],
      "linkedIn": "",
      "website": "",
      "email": "jtsai24@berkeley.edu"
    },
    "25d5a655-3703-4312-9242-f34f110cd95a": {
      "firstName": "Zhuoying",
      "lastName": "Yang",
      "nickname": "Joying",
      "image": "zhuoying-yang-0.jpg",
      "roles": [
        "Senior Advisor"
      ],
      "linkedIn": "https://www.linkedin.com/in/joying-yang",
      "website": "",
      "email": "joying@berkeley.edu"
    },
    "e95b2a00-cc48-41de-9284-783d7548c39f": {
      "firstName": "SuHyang",
      "lastName": "Kim",
      "nickname": "Juliet",
      "image": "suhyang-kim-0.jpg",
      "roles": [
        ""
      ],
      "linkedIn": "https://www.linkedin.com/in/suhyangkim",
      "website": "",
      "email": "suhyang@berkeley.edu"
    },
    "a005fe49-471d-417e-83f4-3a298d49d2c8": {
      "firstName": "Kabir",
      "lastName": "Shah",
      "nickname": "",
      "image": "kabir-shah-0.jpg",
      "roles": [
        "[Exec] VP External"
      ],
      "linkedIn": "http://linkedin.com/in/kabir-shah",
      "website": "https://www.kabir.sh",
      "email": "kabirshah@berkeley.edu"
    },
    "378a6ec4-7c9f-4fff-bed7-534262a0d817": {
      "firstName": "Kartik",
      "lastName": "Aggarwal",
      "nickname": "",
      "image": "kartik-aggarwal-0.jpg",
      "roles": [
        "[External Team] Member",
        "Senior Advisor"
      ],
      "linkedIn": "https://www.linkedin.com/in/-kartikaggarwal/",
      "website": "",
      "email": "kartikaggarwal@berkeley.edu"
    },
    "470a9b54-d100-4225-b7ad-65f6ec3b5f66": {
      "firstName": "Kenzie",
      "lastName": "Tee",
      "nickname": "",
      "image": "kenzie-tee-0.jpg",
      "roles": [
        ""
      ],
      "linkedIn": "",
      "website": "",
      "email": ""
    },
    "116a9427-7f6c-4b96-8e69-19a803901f04": {
      "firstName": "Kimberley",
      "lastName": "Fan",
      "nickname": "",
      "image": "kimberley-fan-0.jpg",
      "roles": [
        "Senior Advisor"
      ],
      "linkedIn": "https://www.linkedin.com/in/kimberleyfan",
      "website": "",
      "email": "kimberley.fan123@berkeley.edu"
    },
    "424e091c-1c5d-4dcf-859d-9f0ea7c54794": {
      "firstName": "Krish",
      "lastName": "Soni",
      "nickname": "",
      "image": "krish-soni-0.jpg",
      "roles": [
        "[Decal] Course Staff"
      ],
      "linkedIn": "",
      "website": "",
      "email": "krish_soni@berkeley.edu"
    },
    "aba47d94-98b1-4edc-b863-6610ed5497e0": {
      "firstName": "Kush",
      "lastName": "Garg",
      "nickname": "Kush",
      "image": "kush-garg-0.jpg",
      "roles": [
        ""
      ],
      "linkedIn": "https://www.linkedin.com/in/kushg02/",
      "website": "https://www.kushgarg.com",
      "email": "kush.garg@berkeley.edu"
    },
    "d1887c59-a3eb-4af6-9a67-d67ff18c1a80": {
      "firstName": "Kyle",
      "lastName": "Kuwahara",
      "nickname": "",
      "image": "kyle-kuwahara-0.jpg",
      "roles": [
        "[MET] Member",
        "[Industry] Backend Developer"
      ],
      "linkedIn": "https://www.linkedin.com/in/ kylekuwahara",
      "website": "",
      "email": "kylekuwahara@berkeley.edu"
    },
    "c47ca211-3f2d-4132-880f-21d94ba4b03a": {
      "firstName": "Laura",
      "lastName": "Pei",
      "nickname": "",
      "image": "laura-pei-0.jpg",
      "roles": [
        ""
      ],
      "linkedIn": "https://www.linkedin.com/in/laurapei/",
      "website": "",
      "email": ""
    },
    "ee474ad4-d064-4a7b-92b8-dcb271ed72e5": {
      "firstName": "Lauren",
      "lastName": "Kim",
      "nickname": "",
      "image": "lauren-kim-0.jpg",
      "roles": [
        "[Exec] VP Bootcamp"
      ],
      "linkedIn": "https://www.linkedin.com/in/laurennayunkim/",
      "website": "https://www.laurennayunkim.com",
      "email": "laurennayunkim@berkeley.edu"
    },
    "04feaf31-cdc9-4ce1-ba10-464c029052bc": {
      "firstName": "Leah",
      "lastName": "Hong",
      "nickname": "",
      "image": "leah-hong-0.jpg",
      "roles": [
        ""
      ],
      "linkedIn": "",
      "website": "",
      "email": "leah6519@berkeley.edu"
    },
    "50cd4dba-4a4c-474e-8ef1-efd75ef87cbf": {
      "firstName": "Leen",
      "lastName": "Armoush",
      "nickname": "",
      "image": "leen-armoush-0.jpg",
      "roles": [
        ""
      ],
      "linkedIn": "https://www.linkedin.com/in/leen-armoush/",
      "website": "",
      "email": "Larmoush@berkeley.edu"
    },
    "4a751c16-2a0e-44c1-9fff-22424f237465": {
      "firstName": "Lizzie",
      "lastName": "Lau",
      "nickname": "",
      "image": "lizzie-lau-0.jpg",
      "roles": [
        ""
      ],
      "linkedIn": "https://www.linkedin.com/in/lizzie-lau/",
      "website": "",
      "email": ""
    },
    "3e7b68ac-5171-45c6-986c-bf9a4bd43280": {
      "firstName": "ManuelDeJesus",
      "lastName": "Muñoz",
      "nickname": "Manuel",
      "image": "manueldejesus-muñoz-0.jpg",
      "roles": [
        "[Industry] Product Manager",
        "[Decal] Course Staff"
      ],
      "linkedIn": "https://www.linkedin.com/in/manuel-munoz-968582236",
      "website": "https://www.manuelmunoz.me/",
      "email": "mannymnz@berkeley.edu"
    },
    "cd0e845d-5b67-48da-b203-05f43cad8071": {
      "firstName": "Marin",
      "lastName": "Lau",
      "nickname": "Marin",
      "image": "marin-lau-0.jpg",
      "roles": [
        "[Industry] Product Manager"
      ],
      "linkedIn": "https://www.linkedin.com/in/marin-lau-42b2bb255/",
      "website": "https://www.sites.google.com/berkeley.edu/marinlau/home",
      "email": "marinlau@berkeley.edu"
    },
    "6bba07bc-9c59-49fe-a049-62f6efa1bbff": {
      "firstName": "Matthew",
      "lastName": "Robillard",
      "nickname": "Matt",
      "image": "matthew-robillard-0.jpg",
      "roles": [
        "[DeCal] Fullstack TA",
        "[Exec] VP Education"
      ],
      "linkedIn": "https://www.linkedin.com/in/matthew-robillard-6723b8252/",
      "website": "https://www.mjrobillard.com",
      "email": "Robillard.matthew22@berkeley.edu"
    },
    "a2f3978c-3d9b-4c99-bfd8-45f8431c29df": {
      "firstName": "Matthew",
      "lastName": "Lee",
      "nickname": "",
      "image": "matthew-lee-0.jpg",
      "roles": [
        ""
      ],
      "linkedIn": "",
      "website": "",
      "email": ""
    },
    "231ea295-306f-4168-a30b-4a9017de5c5c": {
      "firstName": "Max",
      "lastName": "Ye",
      "nickname": "",
      "image": "max-ye-0.jpg",
      "roles": [
        ""
      ],
      "linkedIn": "https://www.linkedin.com/in/maxsye/",
      "website": "https://www.maxye.net",
      "email": "maxye@berkeley.edu"
    },
    "2f53ee72-804b-49c3-994f-02a72ac5ffe1": {
      "firstName": "Meiqi",
      "lastName": "Liang",
      "nickname": "",
      "image": "meiqi-liang-0.jpg",
      "roles": [
        ""
      ],
      "linkedIn": "https://www.linkedin.com/in/meiqi-liang/",
      "website": "",
      "email": "mliang21@berkeley.edu"
    },
    "b1b92bad-b49d-4bbe-95ea-fde6fbf96fb7": {
      "firstName": "Melody",
      "lastName": "Yan",
      "nickname": "",
      "image": "melody-yan-0.jpg",
      "roles": [
        ""
      ],
      "linkedIn": "",
      "website": "",
      "email": ""
    },
    "04fdff3f-8685-4fba-902d-76de55c743be": {
      "firstName": "Michelle",
      "lastName": "Wang",
      "nickname": "",
      "image": "michelle-wang-0.jpg",
      "roles": [
        ""
      ],
      "linkedIn": "https://www.linkedin.com/mwlite/in/michelle-wang-3aa12a227 ",
      "website": "",
      "email": "michelle.wang@berkeley.edu"
    },
    "438fe96d-bea3-4699-8fab-378a5776746f": {
      "firstName": "Minh",
      "lastName": "Nguyen",
      "nickname": "",
      "image": "minh-nguyen-0.jpg",
      "roles": [
        ""
      ],
      "linkedIn": "https://www.linkedin.com/in/minhnguy19",
      "website": "https://www.minhnguy19.github.io/",
      "email": "minhnguy19@berkeley.edu"
    },
    "8b4ab7aa-2e3a-4026-ad2f-4d95339676c7": {
      "firstName": "Naomi",
      "lastName": "Manuel",
      "nickname": "",
      "image": "naomi-manuel-0.jpg",
      "roles": [
        "[Exec] VP Marketing"
      ],
      "linkedIn": "https://www.linkedin.com/in/naomi-m-899a011a5",
      "website": "",
      "email": "naomimanuel@berkeley.edu"
    },
    "1a6a2c3a-510d-4023-b819-f2c31b07ded1": {
      "firstName": "Natalia",
      "lastName": "Shamoon",
      "nickname": "",
      "image": "natalia-shamoon-0.jpg",
      "roles": [
        "[Exec] VP External"
      ],
      "linkedIn": "https://www.linkedin.com/in/natalia-shamoon",
      "website": "",
      "email": "nataliashamoon@berkeley.edu"
    },
    "4731e0e7-cb32-4e91-a7ba-1007c9f4aaf0": {
      "firstName": "Neha",
      "lastName": "Haq",
      "nickname": "",
      "image": "neha-haq-0.jpg",
      "roles": [
        ""
      ],
      "linkedIn": "",
      "website": "",
      "email": ""
    },
    "b27698e9-72fb-46d1-ac11-77c3e51e86d4": {
      "firstName": "Neil",
      "lastName": "Kamdar",
      "nickname": "",
      "image": "neil-kamdar-0.jpg",
      "roles": [
        ""
      ],
      "linkedIn": "https://www.linkedin.com/in/neil-kamdar/",
      "website": "",
      "email": ""
    },
    "bdec5358-17f2-4e7b-8f83-e2cdfd68013c": {
      "firstName": "Nemerjit",
      "lastName": "Singh",
      "nickname": "Nemer",
      "image": "nemerjit-singh-0.jpg",
      "roles": [
        "[Industry] Fullstack Developer"
      ],
      "linkedIn": "https://www.linkedin.com/in/nemerjit-singh",
      "website": "",
      "email": "nemerjitsingh@berkeley.edu"
    },
    "5639a77b-8924-45be-bd70-065a6493b547": {
      "firstName": "Nerissa",
      "lastName": "Hsieh",
      "nickname": "",
      "image": "nerissa-hsieh-0.jpg",
      "roles": [
        ""
      ],
      "linkedIn": "https://www.linkedin.com/in/nerissahsieh/",
      "website": "https://www.nerissahsieh.com/",
      "email": ""
    },
    "78c2a025-7f35-475e-b888-2deb2e6bab8f": {
      "firstName": "Nicholas",
      "lastName": "Shin",
      "nickname": "Nick",
      "image": "nicholas-shin-0.jpg",
      "roles": [
        "[Industry] Fullstack Developer",
        "[MET] Member"
      ],
      "linkedIn": "https://www.linkedin.com/in/nicholas-shin-b998651b2",
      "website": "",
      "email": "nshin02@berkeley.edu"
    },
    "2853436a-8f3b-47f2-a402-972750e89165": {
      "firstName": "Nicholas",
      "lastName": "Galin",
      "nickname": "Nico",
      "image": "nicholas-galin-0.jpg",
      "roles": [
        ""
      ],
      "linkedIn": "https://www.linkedin.com/in/nicholas-galin/",
      "website": "https://www.nicogalin.com",
      "email": "nicholas.galin@berkeley.edu"
    },
    "92308c36-f41a-4a6b-8d93-f585372f6621": {
      "firstName": "Nitya",
      "lastName": "Krishnakumar",
      "nickname": "",
      "image": "nitya-krishnakumar-0.jpg",
      "roles": [
        ""
      ],
      "linkedIn": "https://www.linkedin.com/in/nitya-krish/",
      "website": "",
      "email": "nkrishnakumar@berkeley.edu"
    },
    "0378f8d8-099a-4323-b350-26d27e7be2fe": {
      "firstName": "Prabhas",
      "lastName": "Kurapati",
      "nickname": "",
      "image": "prabhas-kurapati-0.jpg",
      "roles": [
        "[Decal] Course Staff"
      ],
      "linkedIn": "https://www.linkedin.com/in/prabhask/",
      "website": "",
      "email": "prabhask@berkeley.edu"
    },
    "d5ffcb07-1193-48fb-9dc7-d18f698eed72": {
      "firstName": "Pranav",
      "lastName": "Prasad",
      "nickname": "",
      "image": "pranav-prasad-0.jpg",
      "roles": [
        "[Design Team] Member",
        "[Industry] Product Designer"
      ],
      "linkedIn": "https://www.linkedin.com/in/pranav-prasad-476b24271",
      "website": "",
      "email": "pranav.prasad@berkeley.edu"
    },
    "4c76923a-f41d-4e5f-a3b5-e1f878e0128f": {
      "firstName": "Qianyi",
      "lastName": "Chen",
      "nickname": "",
      "image": "qianyi-chen-0.jpg",
      "roles": [
        ""
      ],
      "linkedIn": "",
      "website": "",
      "email": ""
    },
    "ac7c6d61-f265-476f-86ce-4d0b1e8d2126": {
      "firstName": "Rachel",
      "lastName": "Yun",
      "nickname": "Rachel",
      "image": "rachel-yun-0.jpg",
      "roles": [
        "[Industry] Product Designer"
      ],
      "linkedIn": "",
      "website": "",
      "email": "ryun24@berkeley.edu"
    },
    "aec7b7d8-7517-403b-a784-1ebec0402778": {
      "firstName": "Rachel",
      "lastName": "Ng",
      "nickname": "",
      "image": "rachel-ng-0.jpg",
      "roles": [
        ""
      ],
      "linkedIn": "",
      "website": "",
      "email": ""
    },
    "87439d3c-8ad9-4ef2-b4e5-427bf24b35ea": {
      "firstName": "Rachel",
      "lastName": "Quach",
      "nickname": "",
      "image": "rachel-quach-0.jpg",
      "roles": [
        "[Industry] Frontend Developer"
      ],
      "linkedIn": "https://www.linkedin.com/in/rachelquach1/",
      "website": "",
      "email": "racheljquach@berkeley.edu"
    },
    "411dcf8e-7882-4e2f-8aa4-9d3c250ab7f3": {
      "firstName": "Raga",
      "lastName": "Kavari",
      "nickname": "",
      "image": "raga-kavari-0.jpg",
      "roles": [
        ""
      ],
      "linkedIn": "",
      "website": "",
      "email": ""
    },
    "471a81af-f774-432c-b6dc-f79abbb044a8": {
      "firstName": "Cheng-Jui",
      "lastName": "Wan",
      "nickname": "Ray",
      "image": "cheng-jui-wan-0.jpg",
      "roles": [
        "[Decal] Course Staff"
      ],
      "linkedIn": "https://www.linkedin.com/in/ray-wan-23a9121ba",
      "website": "",
      "email": "raywan@berkeley.edu"
    },
    "7e5b322e-4f98-429a-b7c7-70fd0d0b80cb": {
      "firstName": "YoonWha",
      "lastName": "Won",
      "nickname": "Rebecca",
      "image": "yoonwha-won-0.jpg",
      "roles": [
        ""
      ],
      "linkedIn": "",
      "website": "",
      "email": "wyh402@berkeley.edu"
    },
    "ec305529-e647-43b8-9585-7f3754d7e41a": {
      "firstName": "Rex",
      "lastName": "Liu",
      "nickname": "Rex",
      "image": "rex-liu-0.jpg",
      "roles": [
        ""
      ],
      "linkedIn": "https://www.linkedin.com/in/rexliu3",
      "website": "https://www.rexliu.dev",
      "email": "rexliu3@berkeley.edu"
    },
    "1fed49e9-c53d-4743-b5d8-261d8d864bc3": {
      "firstName": "Richa",
      "lastName": "Jos",
      "nickname": "",
      "image": "richa-jos-0.jpg",
      "roles": [
        "[Industry] Fullstack Developer"
      ],
      "linkedIn": "https://www.linkedin.com/in/richa-jos/",
      "website": "",
      "email": "richajos34@berkeley.edu"
    },
    "a03eb7c5-a7b9-40b1-99fa-663c5e878f33": {
      "firstName": "Richard",
      "lastName": "Xue",
      "nickname": "",
      "image": "richard-xue-0.jpg",
      "roles": [
        ""
      ],
      "linkedIn": "",
      "website": "",
      "email": ""
    },
    "fe0eadce-1577-4771-9641-4e3856542b84": {
      "firstName": "Jerrick",
      "lastName": "Zhou",
      "nickname": "Rick",
      "image": "jerrick-zhou-0.jpg",
      "roles": [
        ""
      ],
      "linkedIn": "https://www.ttps://www.linkedin.com/in/rick-zhou-a35208169",
      "website": "",
      "email": ""
    },
    "bdfbc6bc-cf84-4399-8586-8338c86f45e4": {
      "firstName": "Ridge",
      "lastName": "Huang",
      "nickname": "",
      "image": "ridge-huang-0.jpg",
      "roles": [
        "[Industry] Frontend Developer",
        "[Industry] Backend Developer"
      ],
      "linkedIn": "https://www.linkedin.com/in/ridge-huang/",
      "website": "",
      "email": "ridgeh5@berkeley.edu"
    },
    "7f38583b-1535-4b2b-b3b3-e0b6e76cb9c2": {
      "firstName": "Rishi",
      "lastName": "Khare",
      "nickname": "",
      "image": "rishi-khare-0.jpg",
      "roles": [
        ""
      ],
      "linkedIn": "https://www.linkedin.com/in/rishi-khare/",
      "website": "",
      "email": "rishi.khare@berkeley.edu"
    },
    "0982b294-1561-466b-b891-c46746ccb475": {
      "firstName": "Rohan",
      "lastName": "Taneja",
      "nickname": "",
      "image": "rohan-taneja-0.jpg",
      "roles": [
        "Senior Advisor"
      ],
      "linkedIn": "https://www.linkedin.com/in/rohan-taneja/",
      "website": "https://www.rtaneja.com",
      "email": "rohan.taneja@berkeley.edu"
    },
    "dbdc35eb-0928-470c-967b-2918c3c32042": {
      "firstName": "Ryan",
      "lastName": "Huang",
      "nickname": "",
      "image": "ryan-huang-0.jpg",
      "roles": [
        ""
      ],
      "linkedIn": "https://www.linkedin.com/in/ryanhuang36/",
      "website": "",
      "email": "ryanhuang@berkeley.edu"
    },
    "362cf957-a2bc-4b97-ad47-8f392ba7233a": {
      "firstName": "Sajal",
      "lastName": "Ravish",
      "nickname": "",
      "image": "sajal-ravish-0.jpg",
      "roles": [
        ""
      ],
      "linkedIn": "https://www.linkedin.com/in/sajalr",
      "website": "",
      "email": "sajal@berkeley.edu"
    },
    "a06d4435-d86f-4a1f-832b-44d439cec34a": {
      "firstName": "Saketh",
      "lastName": "Panchumarthy",
      "nickname": "",
      "image": "saketh-panchumarthy-0.jpg",
      "roles": [
        "[MET] Member"
      ],
      "linkedIn": "https://www.linkedin.com/in/sakethpanchumarthy",
      "website": "",
      "email": "saketh@berkeley.edu"
    },
    "2802bebc-5aeb-4acf-8565-f7f208e99f64": {
      "firstName": "Samarth",
      "lastName": "Goel",
      "nickname": "",
      "image": "samarth-goel-0.jpg",
      "roles": [
        ""
      ],
      "linkedIn": "https://www.linkedin.com/in/samarth-goel1",
      "website": "https://www.samarthgoel.com",
      "email": "sgoel9@berkeley.edu"
    },
    "8b78ab15-5868-485b-87f2-21092e2860db": {
      "firstName": "Sanjeev",
      "lastName": "Thurgam",
      "nickname": "",
      "image": "sanjeev-thurgam-0.jpg",
      "roles": [
        ""
      ],
      "linkedIn": "https://www.linkedin.com/in/sanjeev-thurgam-1188b0196/",
      "website": "",
      "email": "sanjeevt@berkeley.edu"
    },
    "c56756ad-ecc3-4c90-bf60-416794627eac": {
      "firstName": "Sarah",
      "lastName": "Suen",
      "nickname": "",
      "image": "sarah-suen-0.jpg",
      "roles": [
        "[Design Team] Member"
      ],
      "linkedIn": "https://www.linkedin.com/in/sarahsuen/",
      "website": "",
      "email": "sarahsuen@berkeley.edu"
    },
    "ad012630-e88f-40d3-a1cf-9d5721090ade": {
      "firstName": "Sebastiaan",
      "lastName": "Szafir",
      "nickname": "Sebi",
      "image": "sebastiaan-szafir-0.jpg",
      "roles": [
        "Senior Advisor"
      ],
      "linkedIn": "https://www.linkedin.com/in/sebastiaan-szafir-fridman/",
      "website": "https://www.sebiszafir.com",
      "email": "sebastiaan@berkeley.edu"
    },
    "320a57ff-f393-483b-b792-49080a8c5b9a": {
      "firstName": "Seeun",
      "lastName": "Ahn",
      "nickname": "",
      "image": "seeun-ahn-0.jpg",
      "roles": [
        "[Industry] Product Designer"
      ],
      "linkedIn": "http://www.linkedin.com/in/seeunahn",
      "website": "",
      "email": "seeun@berkeley.edu"
    },
    "872484f8-c377-4768-80de-9fee0f29857a": {
      "firstName": "Siddhant",
      "lastName": "Sharma",
      "nickname": "Sid",
      "image": "siddhant-sharma-0.jpg",
      "roles": [
        ""
      ],
      "linkedIn": "https://www.linkedin.com/in/sharma-sid/",
      "website": "https://www.siddhantsharma.me",
      "email": "siddhantsharma@berkeley.edu"
    },
    "7818b94a-6bf1-42a9-a81d-163d00c000d9": {
      "firstName": "Sinead",
      "lastName": "McCaffery",
      "nickname": "",
      "image": "sinead-mccaffery-0.jpg",
      "roles": [
        "[Industry] Product Manager"
      ],
      "linkedIn": "https://www.linkedin.com/in/sineadmccaffery",
      "website": "",
      "email": "sineadmccaffery@berkeley.edu"
    },
    "709413b9-94ee-45af-bb7e-c13beed6db6e": {
      "firstName": "ChloeSommer",
      "lastName": "Santilla",
      "nickname": "Sommie",
      "image": "chloesommer-santilla-0.jpg",
      "roles": [
        "[MET] Member",
        "[Industry] Product Designer"
      ],
      "linkedIn": "https://www.linkedin.com/in/chloesantilla",
      "website": "",
      "email": "chlosomsantilla@berkeley.edu"
    },
    "ca12fd6f-dd74-41a9-ba9b-e4eef62de171": {
      "firstName": "Sooyeon",
      "lastName": "Oh",
      "nickname": "",
      "image": "sooyeon-oh-0.jpg",
      "roles": [
        ""
      ],
      "linkedIn": "https://www.linkedin.com/in/sooyeonoh",
      "website": "",
      "email": ""
    },
    "b1d3363f-0f5a-4506-912c-783d34fcc962": {
      "firstName": "Sophia",
      "lastName": "Guo",
      "nickname": "",
      "image": "sophia-guo-0.jpg",
      "roles": [
        ""
      ],
      "linkedIn": "https://www.linkedin.com/in/sophiaaguo/",
      "website": "https://www.sophiaguo.com",
      "email": "sophia_guo555@berkeley.edu"
    },
    "60a3d29e-d767-4a5a-8a88-e9714be37047": {
      "firstName": "Sophia",
      "lastName": "Sharifi",
      "nickname": "",
      "image": "sophia-sharifi-0.jpg",
      "roles": [
        ""
      ],
      "linkedIn": "",
      "website": "",
      "email": ""
    },
    "b3b2e88d-476c-476f-affc-3c163098af73": {
      "firstName": "Sophia",
      "lastName": "Sung",
      "nickname": "",
      "image": "sophia-sung-0.jpg",
      "roles": [
        "[Industry] Frontend Developer",
        "[MET] Member"
      ],
      "linkedIn": "https://www.linkedin.com/in/sophia-sung-0948b6212",
      "website": "",
      "email": "sophiasung@berkeley.edu"
    },
    "8c809f26-0530-4d5b-b7b5-b923322e94e9": {
      "firstName": "Stephen",
      "lastName": "Krider",
      "nickname": "",
      "image": "stephen-krider-0.jpg",
      "roles": [
        ""
      ],
      "linkedIn": "https://www.linkedin.com/in/skrider/",
      "website": "",
      "email": ""
    },
    "7d9bbb9d-742d-461e-a241-599ecc2b2e61": {
      "firstName": "Thien",
      "lastName": "Le",
      "nickname": "Thien",
      "image": "thien-le-0.jpg",
      "roles": [
        "[External Team] Member"
      ],
      "linkedIn": "https://www.linkedin.com/mwlite/in/thien-le-91aab21aa",
      "website": "",
      "email": "thienle1942@berkeley.edu"
    },
    "887ed0eb-9bb2-41e2-a29b-18dadd26615a": {
      "firstName": "Tijmen",
      "lastName": "Sep",
      "nickname": "",
      "image": "tijmen-sep-0.jpg",
      "roles": [
        ""
      ],
      "linkedIn": "https://www.linkedin.com/in/jasminewschen/",
      "website": "",
      "email": ""
    },
    "82cba21b-8619-4804-a59b-bbbcbf0ac864": {
      "firstName": "Trevor",
      "lastName": "Trinh",
      "nickname": "",
      "image": "trevor-trinh-0.jpg",
      "roles": [
        ""
      ],
      "linkedIn": "https://www.linkedin.com/in/trevortrinh",
      "website": "https://www.trevx.me",
      "email": "trevortrinh@berkeley.edu"
    },
    "3e09d298-cfd2-4d9c-b3f8-cb6f81195f28": {
      "firstName": "Trisha",
      "lastName": "Sathish",
      "nickname": "",
      "image": "trisha-sathish-0.jpg",
      "roles": [
        "[DeCal] Design TA",
        "[Exec] President"
      ],
      "linkedIn": "https://www.linkedin.com/in/trisha-sathish-36b9021b3/",
      "website": "",
      "email": "trishasathish@berkeley.edu"
    },
    "3c147d88-97fe-4608-bbc1-4bfcf630d103": {
      "firstName": "Vaikundh",
      "lastName": "Jagannathan",
      "nickname": "V",
      "image": "vaikundh-jagannathan-0.jpg",
      "roles": [
        ""
      ],
      "linkedIn": "https://www.linkedin.com/in/vaikundh",
      "website": "",
      "email": "vaikundh.j@berkeley.edu"
    },
    "dbe2fb06-ee53-4972-9459-263295b2e6b5": {
      "firstName": "Vanessa",
      "lastName": "Qiu",
      "nickname": "",
      "image": "vanessa-qiu-0.jpg",
      "roles": [
        ""
      ],
      "linkedIn": "",
      "website": "",
      "email": "vanessaq@berkeley.edu"
    },
    "41ed9bb8-9b00-4d05-bc9a-07b2441fc6ca": {
      "firstName": "Venezia",
      "lastName": "Hartanto",
      "nickname": "Venezia",
      "image": "venezia-hartanto-0.jpg",
      "roles": [
        ""
      ],
      "linkedIn": "",
      "website": "",
      "email": "veneziangela@berkeley.edu"
    },
    "2c953ae0-3030-45c1-b8ca-4f566d813b0d": {
      "firstName": "Victoria",
      "lastName": "Li",
      "nickname": "Vicky",
      "image": "victoria-li-0.jpg",
      "roles": [
        ""
      ],
      "linkedIn": "https://www.linkedin.com/in/victoriayli/",
      "website": "https://www.vickyli.me/",
      "email": "victoria.li@berkeley.edu"
    },
    "5cbeae3e-76da-46d7-8461-b34b2461df3c": {
      "firstName": "Victor",
      "lastName": "Shen",
      "nickname": "",
      "image": "victor-shen-0.jpg",
      "roles": [
        "[Exec] VP Internal"
      ],
      "linkedIn": "https://www.linkedin.com/in/vmshen",
      "website": "https://www.vshen.me",
      "email": "vshen@berkeley.edu"
    },
    "e0f4394e-453d-4966-b28f-805d221a3188": {
      "firstName": "Vihan",
      "lastName": "Bhargava",
      "nickname": "",
      "image": "vihan-bhargava-0.jpg",
      "roles": [
        "Senior Advisor"
      ],
      "linkedIn": "https://www.linkedin.com/in/vihanb/",
      "website": "https://www.vihan.org",
      "email": "vihan@berkeley.edu"
    },
    "911095b3-c707-493f-95c0-30cbfa5cfc52": {
      "firstName": "Vincent",
      "lastName": "Lin",
      "nickname": "",
      "image": "vincent-lin-0.jpg",
      "roles": [
        ""
      ],
      "linkedIn": "https://www.linkedin.com/in/vincentlin83/",
      "website": "",
      "email": "vincentlin83@berkeley.edu"
    },
    "96652f2d-9142-4823-a8cd-60e469b58ebd": {
      "firstName": "Violet",
      "lastName": "Luo",
      "nickname": "",
      "image": "violet-luo-0.jpg",
      "roles": [
        ""
      ],
      "linkedIn": "",
      "website": "",
      "email": ""
    },
    "5f68a209-d554-485e-914f-3302428976ca": {
      "firstName": "Waleed",
      "lastName": "Latif",
      "nickname": "",
      "image": "waleed-latif-0.jpg",
      "roles": [
        ""
      ],
      "linkedIn": "",
      "website": "",
      "email": ""
    },
    "10eceb4d-85cc-47b9-a7a9-b5b0d0e9e9be": {
      "firstName": "William",
      "lastName": "Henderson",
      "nickname": "Will",
      "image": "william-henderson-0.jpg",
      "roles": [
        ""
      ],
      "linkedIn": "",
      "website": "https://www.william-henderson.com",
      "email": "william_henderson@berkeley.edu"
    },
    "fca53986-c227-4be1-b1b6-95dc3a59b043": {
      "firstName": "William",
      "lastName": "Louis",
      "nickname": "Will",
      "image": "william-louis-0.jpg",
      "roles": [
        ""
      ],
      "linkedIn": "https://www.linkedin.com/in/william-l-549860132/",
      "website": "",
      "email": "wlouis23@berkeley.edu"
    },
    "aec7f480-0b6b-4a79-b876-ac5303ba283f": {
      "firstName": "Youngjun",
      "lastName": "Seo",
      "nickname": "",
      "image": "youngjun-seo-0.jpg",
      "roles": [
        ""
      ],
      "linkedIn": "https://www.linkedin.com/in/youngjun-seo-9170a91a1",
      "website": "",
      "email": ""
    },
    "d07fb1a1-c8c8-4036-9e56-c1a8822bf3bd": {
      "firstName": "Yu-Cian",
      "lastName": "Liu",
      "nickname": "Yucian",
      "image": "yu-cian-liu-0.jpg",
      "roles": [
        "[DeCal] Design TA",
        "[Exec] President"
      ],
      "linkedIn": "",
      "website": "",
      "email": "yucianliu@berkeley.edu"
    },
    "b1b53ffc-ebd8-4e0c-a5dd-a295328397fb": {
      "firstName": "Yuto",
      "lastName": "Nishida",
      "nickname": "",
      "image": "yuto-nishida-0.jpg",
      "roles": [
        "Senior Advisor"
      ],
      "linkedIn": "https://www.linkedin.com/in/yuton",
      "website": "https://www.yart.me/",
      "email": "yuto@berkeley.edu"
    },
    "80cc00cd-8d7d-4d29-8d30-cce2ceee52da": {
      "firstName": "Zayna",
      "lastName": "Lateef",
      "nickname": "",
      "image": "zayna-lateef-0.jpg",
      "roles": [
        "[DeCal] Fullstack TA",
        "[Exec] VP Education"
      ],
      "linkedIn": "https://www.linkedin.com/in/zayna-lateef-942756216/ ",
      "website": "",
      "email": "zayna.lateef@berkeley.edu"
    }
  },
  "teams": {
    "seniorAdvisors": [
      "231d19ef-5d6f-45d8-9c28-44c571987b27",
      "3090cfbf-9fe9-4a0b-9599-6b956b3a9d0c",
      "fc1e6f95-5563-40e5-badf-bb6fd8477842",
      "ccf2e74e-e2ed-4e67-b51a-abb961f25022",
      "cf42a5e4-e388-466c-948f-5a81cf78a424",
      "25d5a655-3703-4312-9242-f34f110cd95a",
      "378a6ec4-7c9f-4fff-bed7-534262a0d817",
      "116a9427-7f6c-4b96-8e69-19a803901f04",
      "0982b294-1561-466b-b891-c46746ccb475",
      "ad012630-e88f-40d3-a1cf-9d5721090ade",
      "e0f4394e-453d-4966-b28f-805d221a3188",
      "b1b53ffc-ebd8-4e0c-a5dd-a295328397fb"
    ],
    "alumni": [
      "b26925d9-ed5a-4c18-bcc0-cccf929d06c9",
      "6e486461-c847-4eb4-b0c0-dea09904ecf8",
      "0421f855-bba2-40b7-87c7-303bbc99f95e",
      "4947071e-4886-4af5-95bd-bf907dedb474",
      "ed69747d-dd74-464f-8b79-81fc2e00d773",
      "a6c64e23-03dd-4a47-a5f5-bb416c58d338",
      "c2e00e6b-976e-47c5-be2f-efc6d08af327",
      "18e74d58-2799-406c-8239-555726efba42",
      "044913a7-b349-4d23-b1ea-0402e55127ed",
      "a85e67c9-5246-480f-b64c-be76fe8e8cfb",
      "89b3a373-1f45-4bca-9a8f-a56b04ca3380",
      "fec43be9-6273-49a3-84fe-6d8e9741d43d",
      "87a82a09-9462-4d99-8ebf-b46a6d458b43",
      "e8ba4d2d-0a97-470b-8ddc-68b04a837643",
      "58dba9e7-b85b-4a50-b35e-5442e6c3635a",
      "4fe84e26-f0fc-4090-a03a-bd55a5e523a4",
      "97ae6e72-57cd-4249-a8f4-a5a497405638",
      "519190da-3933-48d3-9fb2-c0dbce64316c",
      "5143a5c1-9f07-4371-bd16-47eb044ab280",
      "77162a8b-2651-4bfa-9d8a-b7f75fe1f954",
      "96409aab-4cfe-4069-8953-f1249dd6727b",
      "95760de0-4e8f-40a6-8116-8d0ec6133e41",
      "0bf8c341-e30e-4655-b20c-e57c97e9e650",
      "9cba7420-3a5d-439a-86d1-fa7fa3ad9920",
      "61662ea7-9daa-41d6-9bde-c61c1a7673e1",
      "1c573912-17b2-48af-8548-780f62243457",
      "69feb8b3-5b2b-43c3-a2b8-405d011cfe06",
      "4ac17b82-3776-403a-8926-09752efb41b4",
      "b1b77402-80e8-4d9c-ac44-a591a045633d",
      "52dc0651-09e5-42d8-bfb3-1ca34cf44d6e",
      "72ad1dda-5b34-4330-8f36-0ed9265df32f",
      "679cf4da-672c-4e50-9a62-003b278668bc",
      "6ceb24d4-6e5c-466e-9e98-0d268434392f",
      "6897bfe7-8b92-4137-ac4f-87165cb55c6d",
      "f570c49b-4dc4-4911-8e35-7f96369d873a",
      "965ee02b-381f-4cfd-ac05-b207bd850e75",
      "eaadbbd1-9dfb-40f1-898f-735a78752a39",
      "e33c7668-d94d-45d9-b73c-de84e847f91c",
      "b8a78c51-a7e4-443d-a822-c499084a9ec8",
      "3ac9716b-c6d7-4e89-8ee7-960eb9942c02",
      "1c6a78b6-d715-4b75-8ad6-0e3c1ec17acf",
      "c4e9ec3c-8641-4229-9bf0-a1d8d3a2f914",
      "da68c925-5139-492d-8006-1b6b3b52a866",
      "e95b2a00-cc48-41de-9284-783d7548c39f",
      "470a9b54-d100-4225-b7ad-65f6ec3b5f66",
      "aba47d94-98b1-4edc-b863-6610ed5497e0",
      "c47ca211-3f2d-4132-880f-21d94ba4b03a",
      "04feaf31-cdc9-4ce1-ba10-464c029052bc",
      "50cd4dba-4a4c-474e-8ef1-efd75ef87cbf",
      "4a751c16-2a0e-44c1-9fff-22424f237465",
      "a2f3978c-3d9b-4c99-bfd8-45f8431c29df",
      "231ea295-306f-4168-a30b-4a9017de5c5c",
      "2f53ee72-804b-49c3-994f-02a72ac5ffe1",
      "b1b92bad-b49d-4bbe-95ea-fde6fbf96fb7",
      "04fdff3f-8685-4fba-902d-76de55c743be",
      "438fe96d-bea3-4699-8fab-378a5776746f",
      "4731e0e7-cb32-4e91-a7ba-1007c9f4aaf0",
      "b27698e9-72fb-46d1-ac11-77c3e51e86d4",
      "5639a77b-8924-45be-bd70-065a6493b547",
      "2853436a-8f3b-47f2-a402-972750e89165",
      "92308c36-f41a-4a6b-8d93-f585372f6621",
      "4c76923a-f41d-4e5f-a3b5-e1f878e0128f",
      "aec7b7d8-7517-403b-a784-1ebec0402778",
      "411dcf8e-7882-4e2f-8aa4-9d3c250ab7f3",
      "7e5b322e-4f98-429a-b7c7-70fd0d0b80cb",
      "ec305529-e647-43b8-9585-7f3754d7e41a",
      "a03eb7c5-a7b9-40b1-99fa-663c5e878f33",
      "fe0eadce-1577-4771-9641-4e3856542b84",
      "7f38583b-1535-4b2b-b3b3-e0b6e76cb9c2",
      "dbdc35eb-0928-470c-967b-2918c3c32042",
      "362cf957-a2bc-4b97-ad47-8f392ba7233a",
      "2802bebc-5aeb-4acf-8565-f7f208e99f64",
      "8b78ab15-5868-485b-87f2-21092e2860db",
      "872484f8-c377-4768-80de-9fee0f29857a",
      "ca12fd6f-dd74-41a9-ba9b-e4eef62de171",
      "b1d3363f-0f5a-4506-912c-783d34fcc962",
      "60a3d29e-d767-4a5a-8a88-e9714be37047",
      "8c809f26-0530-4d5b-b7b5-b923322e94e9",
      "887ed0eb-9bb2-41e2-a29b-18dadd26615a",
      "82cba21b-8619-4804-a59b-bbbcbf0ac864",
      "3c147d88-97fe-4608-bbc1-4bfcf630d103",
      "dbe2fb06-ee53-4972-9459-263295b2e6b5",
      "41ed9bb8-9b00-4d05-bc9a-07b2441fc6ca",
      "2c953ae0-3030-45c1-b8ca-4f566d813b0d",
      "911095b3-c707-493f-95c0-30cbfa5cfc52",
      "96652f2d-9142-4823-a8cd-60e469b58ebd",
      "5f68a209-d554-485e-914f-3302428976ca",
      "10eceb4d-85cc-47b9-a7a9-b5b0d0e9e9be",
      "fca53986-c227-4be1-b1b6-95dc3a59b043",
      "aec7f480-0b6b-4a79-b876-ac5303ba283f"
    ],
    "execMembers": [
      "a86d7c13-cf31-4c79-8c95-a1dfcde7381a",
      "23978789-c7df-4596-a6dc-0d1241436081",
      "0380b5db-9eed-4b9c-a840-b538dd766ab2",
      "41316dcb-9acb-44d8-88bb-7e6241759316",
      "a005fe49-471d-417e-83f4-3a298d49d2c8",
      "ee474ad4-d064-4a7b-92b8-dcb271ed72e5",
      "6bba07bc-9c59-49fe-a049-62f6efa1bbff",
      "8b4ab7aa-2e3a-4026-ad2f-4d95339676c7",
      "1a6a2c3a-510d-4023-b819-f2c31b07ded1",
      "3e09d298-cfd2-4d9c-b3f8-cb6f81195f28",
      "5cbeae3e-76da-46d7-8461-b34b2461df3c",
      "d07fb1a1-c8c8-4036-9e56-c1a8822bf3bd",
      "80cc00cd-8d7d-4d29-8d30-cce2ceee52da"
    ],
    "productManagers": [
      "9abba05a-21a7-482f-b85c-7dcece75e52f",
      "092ee936-7c05-4396-95d7-efb9a036d77f",
      "aad57f0e-745e-433c-a8cc-b8bc423920ee",
      "d900637f-a6d1-412e-817c-92d4096027e6",
      "3e7b68ac-5171-45c6-986c-bf9a4bd43280",
      "cd0e845d-5b67-48da-b203-05f43cad8071",
      "7818b94a-6bf1-42a9-a81d-163d00c000d9"
    ],
    "industryMembers": [
      "b667697e-b463-4311-844d-dc399ecdfe68",
      "d1887c59-a3eb-4af6-9a67-d67ff18c1a80",
      "bdec5358-17f2-4e7b-8f83-e2cdfd68013c",
      "78c2a025-7f35-475e-b888-2deb2e6bab8f",
      "d5ffcb07-1193-48fb-9dc7-d18f698eed72",
      "ac7c6d61-f265-476f-86ce-4d0b1e8d2126",
      "87439d3c-8ad9-4ef2-b4e5-427bf24b35ea",
      "1fed49e9-c53d-4743-b5d8-261d8d864bc3",
      "bdfbc6bc-cf84-4399-8586-8338c86f45e4",
      "320a57ff-f393-483b-b792-49080a8c5b9a",
      "709413b9-94ee-45af-bb7e-c13beed6db6e",
      "b3b2e88d-476c-476f-affc-3c163098af73"
    ],
    "bootcampMembers": [],
    "courseStaff": [
      "94b3ddba-5af1-48e8-9b9f-7c6d952ec9ec",
      "44402e83-d106-4e1e-9296-60178c66b677",
      "d28e29cd-c8a9-41ac-8f3a-1294dccce610",
      "198a392a-150e-4d41-b7aa-f3cdcb4e0ee8",
      "2d4e93a0-7fed-47c2-8ac9-be2cd72a1f23",
      "3805c4a9-a2e6-4b8e-a698-7cf5843dd63e",
      "4cde5e51-5318-4cc1-8f2b-e286c0efd837",
      "46f88ea2-06f3-4f0a-9db1-d17d1f4cbce7",
      "424e091c-1c5d-4dcf-859d-9f0ea7c54794",
      "3e7b68ac-5171-45c6-986c-bf9a4bd43280",
      "6bba07bc-9c59-49fe-a049-62f6efa1bbff",
      "0378f8d8-099a-4323-b350-26d27e7be2fe",
      "471a81af-f774-432c-b6dc-f79abbb044a8",
      "3e09d298-cfd2-4d9c-b3f8-cb6f81195f28",
      "d07fb1a1-c8c8-4036-9e56-c1a8822bf3bd",
      "80cc00cd-8d7d-4d29-8d30-cce2ceee52da"
    ],
    "memExperienceTeam": [
      "acf8db27-8965-44f7-b16b-bf87995231e6",
      "44402e83-d106-4e1e-9296-60178c66b677",
      "cb5e4030-4d8e-4066-a729-fb3789b90968",
      "17864f2d-c332-4d1b-8509-6b1b90a06953",
      "d28e29cd-c8a9-41ac-8f3a-1294dccce610",
      "96586d35-e9c8-4310-a464-4db13bc9a924",
      "d1887c59-a3eb-4af6-9a67-d67ff18c1a80",
      "78c2a025-7f35-475e-b888-2deb2e6bab8f",
      "a06d4435-d86f-4a1f-832b-44d439cec34a",
      "709413b9-94ee-45af-bb7e-c13beed6db6e",
      "b3b2e88d-476c-476f-affc-3c163098af73"
    ],
    "designTeam": [
      "d5ffcb07-1193-48fb-9dc7-d18f698eed72",
      "c56756ad-ecc3-4c90-bf60-416794627eac"
    ],
    "externalTeam": [
      "092ee936-7c05-4396-95d7-efb9a036d77f",
      "d900637f-a6d1-412e-817c-92d4096027e6",
      "378a6ec4-7c9f-4fff-bed7-534262a0d817",
      "7d9bbb9d-742d-461e-a241-599ecc2b2e61"
    ]
  }
}